geojson_elevation-0.1.dist-info/METADATA
geojson_elevation-0.1.dist-info/RECORD
geojson_elevation-0.1.dist-info/DESCRIPTION.rst
geojson_elevation-0.1.dist-info/top_level.txt
geojson_elevation-0.1.dist-info/WHEEL
geojson_elevation-0.1.dist-info/metadata.json
geojson_elevation/version.py
geojson_elevation/__init__.py
geojson_elevation/geometry.py
geojson_elevation/backends/__init__.py
geojson_elevation/backends/google.py
