Metadata-Version: 2.0
Name: geojson-elevation
Version: 0.1
Summary: GeoJSON compatible elevation proxy 
Home-page: https://github.com/ninuxorg/python-geojson-elevation
Author: Federico Capoano (nemesisdesign) & Martín Peveri (mapeveri)
Author-email: ninux-dev@ml.ninux.org
License: MIT
Platform: UNKNOWN
Classifier: Development Status :: 1 - Planning
Classifier: Environment :: Console
Classifier: Intended Audience :: Developers
Classifier: License :: OSI Approved :: MIT License
Classifier: Operating System :: OS Independent
Classifier: Programming Language :: Python
Classifier: Topic :: System :: Networking
Requires-Dist: requests
